kitpdf/__init__.py
kitpdf/data/Brewfile
kitpdf/data/Puntos.png
kitpdf/data/tests/5.2M.pdf
kitpdf/data/tests/BBVA.pdf
kitpdf/data/tests/BBVA.png
kitpdf/data/tests/Biosalud Stamp Transparent.png
kitpdf/data/tests/Biosalud Stamp.png
kitpdf/data/tests/ING.pdf
kitpdf/data/tests/folded.png
kitpdf/data/tests/ing1.pdf
kitpdf/data/tests/ing2.pdf
kitpdf/data/tests/ing3.pdf
kitpdf/data/tests/generated/BBVA-picture_paste.png
kitpdf/data/tests/generated/BBVA-putalpha_random.png
kitpdf/data/tests/generated/BBVA-white_alpha-picture_paste.png
kitpdf/data/tests/generated/BBVA-white_alpha.png
kitpdf/data/tests/generated/BioSalud Stamp Transparent-picture_paste.png
kitpdf/data/tests/generated/Biosalud Stamp-white_alpha.png
kitpdf/data/tests/generated/folded-BBVA-picture_paste.png
kitpdf/data/tests/generated/scanned_5.2M.pdf
kitpdf/data/tests/generated/scanned_BBVA.pdf
kitpdf/data/tests/generated/scanned_ING.pdf
kitpdf/data/tests/generated/scanned_ing1.pdf
kitpdf/data/tests/generated/scanned_ing2.pdf
kitpdf/data/tests/generated/scanned_ing3.pdf
kitpdf-0.1.22.dist-info/LICENSE
kitpdf-0.1.22.dist-info/METADATA
kitpdf-0.1.22.dist-info/WHEEL
kitpdf-0.1.22.dist-info/top_level.txt
kitpdf-0.1.22.dist-info/RECORD
