Metadata-Version: 2.1
Name: kitpdf
Version: 0.1.22
Summary: PDF helpers and utils
Author-email: José Antonio Puértolas Montañés <63794670+j5pu@users.noreply.github.com>
License: MIT
Project-URL: Homepage, https://github.com/j5pu/pdfbox
Requires-Python: >=3.11
License-File: LICENSE
Requires-Dist: python-dateutil <3,>=2.8.2
Requires-Dist: fonttools <5,>=4.42.1
Requires-Dist: matplotlib <4,>=3.8.0
Requires-Dist: nodeps
Requires-Dist: pillow <11,>=10.0.0
Requires-Dist: pikepdf <9,>=8.7.1
Requires-Dist: PyMuPDF <2,>=1.23.3
Requires-Dist: pymupdf-fonts <2,>=1.0.5
Provides-Extra: dev
Requires-Dist: nodeps[all,dev] ; extra == 'dev'
